rust_markdown_text_puller-0.1.3.dist-info/METADATA
rust_markdown_text_puller-0.1.3.dist-info/WHEEL
markdown_text_puller.cpython-35m-x86_64-linux-gnu.so
rust_markdown_text_puller-0.1.3.dist-info/RECORD
