Metadata-Version: 2.1
Name: rust-markdown-text-puller
Version: 0.1.3
Classifier: Programming Language :: Python
Classifier: License :: OSI Approved :: MIT License
Summary: A markdown text extractor written in Rust
Author: Eamonn Nugent <eamonn.nugent@demilletech.net>
Author-Email: Eamonn Nugent <eamonn.nugent@demilletech.net>
